ao/__init__.py
ao-1.0.1.dist-info/LICENSE
ao-1.0.1.dist-info/METADATA
ao-1.0.1.dist-info/WHEEL
ao-1.0.1.dist-info/RECORD
