Metadata-Version: 2.1
Name: ao
Version: 1.0.1
Summary: Import the wikipedia summary.
Home-page: https://github.com/tomhea/ao
License: BSD-2-Clause-Simplified
Keywords: ask,questions
Author: Tom Herman
Author-email: flipjumpproject@gmail.com
Requires-Python: >=3.7,<4.0
Classifier: License :: Other/Proprietary License
Classifier: Natural Language :: English
Classifier: Operating System :: OS Independent
Classifier: Programming Language :: Python :: 3
Classifier: Programming Language :: Python :: 3.7
Classifier: Programming Language :: Python :: 3.8
Classifier: Programming Language :: Python :: 3.9
Classifier: Programming Language :: Python :: 3.10
Classifier: Programming Language :: Python :: 3.11
Classifier: Programming Language :: Python :: 3.12
Classifier: Topic :: Internet :: WWW/HTTP :: Dynamic Content :: Wiki
Classifier: Topic :: Internet :: WWW/HTTP :: Indexing/Search
Classifier: Topic :: Software Development :: Libraries
Requires-Dist: requests (==2.31.0)
Project-URL: Repository, https://github.com/tomhea/ao
